aldjemy/__init__.py
aldjemy/apps.py
aldjemy/core.py
aldjemy/meta.py
aldjemy/orm.py
aldjemy/session.py
aldjemy/sqlite.py
aldjemy/table.py
aldjemy/wrapper.py
aldjemy-3.2.dist-info/METADATA
aldjemy-3.2.dist-info/WHEEL
aldjemy-3.2.dist-info/licenses/LICENSE
aldjemy-3.2.dist-info/RECORD
