Metadata-Version: 2.3
Name: aldjemy
Version: 3.2
Summary: SQLAlchemy for your Django models
Project-URL: homepage, https://github.com/aldjemy/aldjemy
Project-URL: repository, https://github.com/aldjemy/aldjemy
Author: Mikhail Krivushin
License: BSD-3-Clause
Requires-Python: >=3.8
Requires-Dist: django>=4.1
Requires-Dist: sqlalchemy<2,>=1.4
